LICENSE
MANIFEST.in
README.md
setup.cfg
setup.py
RandomIO/RandomIO.py
RandomIO/__init__.py
RandomIO/version.py
RandomIO.egg-info/PKG-INFO
RandomIO.egg-info/SOURCES.txt
RandomIO.egg-info/dependency_links.txt
RandomIO.egg-info/requires.txt
RandomIO.egg-info/top_level.txt
bin/IOTools.py