Metadata-Version: 1.1
Name: RandomIO
Version: 0.2.1
Summary: Random file and byte string generator.
Home-page: https://github.com/Storj/RandomIO
Author: William James
Author-email: jameswt@gmail.com
License: The MIT License (MIT)
